nepali_news_scrapers/__init__.py
nepali_news_scrapers/JSONS/ekantipur_आग_म_बज_ट__20250219-185227.json
nepali_news_scrapers/JSONS/ekantipur_आग_म_वर_षक_20250219-185159.json
nepali_news_scrapers/JSONS/ekantipur_एक_हज_र_क__20250219-185226.json
nepali_news_scrapers/JSONS/ekantipur_एनस_लल_स_र_20250219-185246.json
nepali_news_scrapers/JSONS/ekantipur_एप_पलल_ल_य_20250219-185235.json
nepali_news_scrapers/JSONS/ekantipur_क_लम_नल_सर_20250219-185232.json
nepali_news_scrapers/JSONS/ekantipur_क_स_नल_ई_ब_20250219-185211.json
nepali_news_scrapers/JSONS/ekantipur_घरब_सल_ज_ग_20250219-185158.json
nepali_news_scrapers/JSONS/ekantipur_ज_स_ब_एनएक_20250219-185238.json
nepali_news_scrapers/JSONS/ekantipur_जगद_ल_ल_क__20250219-185231.json
nepali_news_scrapers/JSONS/ekantipur_ठ_ल_आय_जन__20250219-185232.json
nepali_news_scrapers/JSONS/ekantipur_द_वय_न_इन__20250219-185217.json
nepali_news_scrapers/JSONS/ekantipur_न_प_ल_बज_र_20250219-185246.json
nepali_news_scrapers/JSONS/ekantipur_ब_ढ_पह_र_ब_20250219-185227.json
nepali_news_scrapers/JSONS/ekantipur_ब_ढ_ल_क_षत_20250219-185208.json
nepali_news_scrapers/JSONS/ekantipur_ब_र_न_ड_म__20250219-185241.json
nepali_news_scrapers/JSONS/ekantipur_ब_व_ईड_क_ड_20250219-185246.json
nepali_news_scrapers/JSONS/ekantipur_बज_रम_बज_ज_20250219-185244.json
nepali_news_scrapers/JSONS/ekantipur_बज_रम_स_मस_20250219-185247.json
nepali_news_scrapers/JSONS/ekantipur_म_आब_ज_ब_ट_20250219-185225.json
nepali_news_scrapers/JSONS/ekantipur_यल_म_यर_स__20250219-185245.json
nepali_news_scrapers/JSONS/ekantipur_र_ष_ट_र_य__20250219-185220.json
nepali_news_scrapers/JSONS/ekantipur_ल_ख_सम_त_क_20250219-185234.json
nepali_news_scrapers/JSONS/ekantipur_लग_त_र_त_स_20250219-185228.json
nepali_news_scrapers/JSONS/ekantipur_व_द_ध_श_रम_20250219-185245.json
nepali_news_scrapers/JSONS/ekantipur_स_प_र_आय_त_20250219-185234.json
nepali_news_scrapers/JSONS/ekantipur_सरक_र_स_यन_20250219-185204.json
nepali_news_scrapers/JSONS/ekantipur_ह_इड_र_प_व_20250219-185234.json
nepali_news_scrapers-0.1.6.dist-info/METADATA
nepali_news_scrapers-0.1.6.dist-info/WHEEL
nepali_news_scrapers-0.1.6.dist-info/RECORD
