Metadata-Version: 2.3
Name: nepali-news-scrapers
Version: 0.1.6
Summary: 
Author: codera21
Author-email: atul.nepal@gmail.com
Requires-Python: >=3.11
Classifier: Programming Language :: Python :: 3
Classifier: Programming Language :: Python :: 3.11
Classifier: Programming Language :: Python :: 3.12
Classifier: Programming Language :: Python :: 3.13
Requires-Dist: bs4 (>=0.0.2,<0.0.3)
Requires-Dist: click (>=8.1.8,<9.0.0)
Requires-Dist: nepali (>=1.1.2,<2.0.0)
Requires-Dist: requests (>=2.32.3,<3.0.0)
